clippie/__init__.py
clippie/main.py
clippie-0.0.2.dist-info/LICENSE
clippie-0.0.2.dist-info/METADATA
clippie-0.0.2.dist-info/WHEEL
clippie-0.0.2.dist-info/entry_points.txt
clippie-0.0.2.dist-info/top_level.txt
clippie-0.0.2.dist-info/RECORD
