Metadata-Version: 2.1
Name: clippie
Version: 0.0.2
Summary: A small API to load and search for similar products based on TF-IDF algorithm
Home-page: https://github.com/mloyanich/online-retail-app
Author: Masha Loianych
Author-email: m.loianych@gmail.com
Project-URL: Bug Tracker, https://github.com/mloyanich/online-retail-app/issues
Keywords: Retail Data application
Classifier: Programming Language :: Python :: 3
Classifier: License :: OSI Approved :: MIT License
Classifier: Operating System :: OS Independent
Requires-Python: >=3.6
License-File: LICENSE
Requires-Dist: uvicorn
Requires-Dist: fastapi
Requires-Dist: pandas
Requires-Dist: pyspark
Requires-Dist: openpyxl
